{
    "fluentMethods": true,
    "relationships": [],
    "fields": [
        {
            "fieldName": "code",
            "fieldType": "String",
            "fieldValidateRules": [
                "required"
            ]
        },
        {
            "fieldName": "name",
            "fieldType": "String",
            "fieldValidateRules": [
                "required"
            ]
        },
        {
            "fieldName": "join_time",
            "fieldType": "LocalDate",
            "fieldValidateRules": [
                "required"
            ]
        }
    ],
    "changelogDate": "20171205084538",
    "dto": "no",
    "service": "no",
    "entityTableName": "customer",
    "pagination": "no"
}
